kaioretry/__init__.py
kaioretry/context.py
kaioretry/decorator.py
kaioretry/py.typed
kaioretry/types.py
kaioretry-1.2.1.dist-info/LICENSE
kaioretry-1.2.1.dist-info/METADATA
kaioretry-1.2.1.dist-info/WHEEL
kaioretry-1.2.1.dist-info/RECORD
