Metadata-Version: 2.3
Name: kaioretry
Version: 1.2.1
Summary: All in one retry and aioretry decorators
License: LGPL-2.1-or-later
Keywords: retry,decorator,asyncio
Author: Damien Nadé
Author-email: anvil.github+kaioretry@livna.org
Requires-Python: >=3.11
Classifier: Development Status :: 5 - Production/Stable
Classifier: Framework :: AsyncIO
Classifier: Intended Audience :: Developers
Classifier: Programming Language :: Python
Classifier: Programming Language :: Python :: 3 :: Only
Classifier: Programming Language :: Python :: 3
Classifier: Programming Language :: Python :: 3.13
Classifier: Programming Language :: Python :: 3.12
Classifier: Programming Language :: Python :: 3.11
Classifier: Topic :: Software Development
Classifier: Typing :: Typed
Requires-Dist: mypy-extensions (>=1)
Requires-Dist: typing_extensions (>=4.5.0)
Project-URL: Documentation, https://kaioretry.readthedocs.io/en/latest/
Project-URL: Issues, https://github.com/Anvil/kaioretry/issues
Project-URL: Repository, https://github.com/Anvil/kaioretry/
